huaweicloudsdkcloudpipeline/__init__.py
huaweicloudsdkcloudpipeline/v2/__init__.py
huaweicloudsdkcloudpipeline/v2/cloudpipeline_async_client.py
huaweicloudsdkcloudpipeline/v2/cloudpipeline_client.py
huaweicloudsdkcloudpipeline/v2/model/__init__.py
huaweicloudsdkcloudpipeline/v2/model/batch_show_pipelines_latest_status_request.py
huaweicloudsdkcloudpipeline/v2/model/batch_show_pipelines_latest_status_response.py
huaweicloudsdkcloudpipeline/v2/model/batch_show_pipelines_status_request.py
huaweicloudsdkcloudpipeline/v2/model/batch_show_pipelines_status_response.py
huaweicloudsdkcloudpipeline/v2/model/code_source.py
huaweicloudsdkcloudpipeline/v2/model/code_source_params.py
huaweicloudsdkcloudpipeline/v2/model/constraint.py
huaweicloudsdkcloudpipeline/v2/model/create_pipeline_by_template_id_request.py
huaweicloudsdkcloudpipeline/v2/model/create_pipeline_by_template_id_response.py
huaweicloudsdkcloudpipeline/v2/model/create_pipeline_by_template_request.py
huaweicloudsdkcloudpipeline/v2/model/create_pipeline_by_template_response.py
huaweicloudsdkcloudpipeline/v2/model/custom_variable.py
huaweicloudsdkcloudpipeline/v2/model/delete_pipeline_request.py
huaweicloudsdkcloudpipeline/v2/model/delete_pipeline_response.py
huaweicloudsdkcloudpipeline/v2/model/job_run.py
huaweicloudsdkcloudpipeline/v2/model/list_pipeline_query.py
huaweicloudsdkcloudpipeline/v2/model/list_pipeline_runs_page_build_params.py
huaweicloudsdkcloudpipeline/v2/model/list_pipeline_runs_page_pipeline_runs.py
huaweicloudsdkcloudpipeline/v2/model/list_pipeline_runs_page_stage_status_list.py
huaweicloudsdkcloudpipeline/v2/model/list_pipeline_runs_query.py
huaweicloudsdkcloudpipeline/v2/model/list_pipeline_runs_request.py
huaweicloudsdkcloudpipeline/v2/model/list_pipeline_runs_response.py
huaweicloudsdkcloudpipeline/v2/model/list_pipeline_simple_info_request.py
huaweicloudsdkcloudpipeline/v2/model/list_pipeline_simple_info_request_body.py
huaweicloudsdkcloudpipeline/v2/model/list_pipeline_simple_info_response.py
huaweicloudsdkcloudpipeline-3.1.58.dist-info/LICENSE
huaweicloudsdkcloudpipeline-3.1.58.dist-info/METADATA
huaweicloudsdkcloudpipeline-3.1.58.dist-info/WHEEL
huaweicloudsdkcloudpipeline-3.1.58.dist-info/top_level.txt
huaweicloudsdkcloudpipeline-3.1.58.dist-info/RECORD
